VisualCrossing/__init__.py
VisualCrossing/_api.py
VisualCrossing/_config.py
VisualCrossing/api.py
VisualCrossing/errors.py
VisualCrossing/version.py
VisualCrossing-0.1.0b0.dist-info/LICENSE
VisualCrossing-0.1.0b0.dist-info/METADATA
VisualCrossing-0.1.0b0.dist-info/WHEEL
VisualCrossing-0.1.0b0.dist-info/top_level.txt
VisualCrossing-0.1.0b0.dist-info/RECORD
