Metadata-Version: 2.1
Name: VisualCrossing
Version: 0.1.0b0
Summary: A python wrapper for fetching weather data from VisualCrossing
Home-page: https://github.com/ZenithClown/VisualCrossing
Author: Debmalya Pramanik
Author-email: dPramanik.official@gmail.com
License: MIT License
Project-URL: Bug Tracker, https://github.com/ZenithClown/VisualCrossing/issues
Keywords: weather-api,weather-forecast,visual-crossing,api-rest,wrapper
Platform: UNKNOWN
Classifier: Development Status :: 4 - Beta
Classifier: Programming Language :: Python :: 3
Classifier: License :: OSI Approved :: MIT License
Requires-Python: >=3.7
Requires-Dist: requests
